{
	"name": "pl_3",
	"properties": {
		"activities": [
			{
				"name": "if",
				"type": "IfCondition",
				"dependsOn": [],
				"userProperties": [],
				"typeProperties": {
					"expression": {
						"value": "@equals(pipeline().globalParameters.glpr1,5)",
						"type": "Expression"
					},
					"ifFalseActivities": [
						{
							"name": "Wait1",
							"type": "Wait",
							"dependsOn": [],
							"userProperties": [],
							"typeProperties": {
								"waitTimeInSeconds": 2
							}
						}
					],
					"ifTrueActivities": [
						{
							"name": "Set variable1",
							"type": "SetVariable",
							"dependsOn": [],
							"policy": {
								"secureOutput": false,
								"secureInput": false
							},
							"userProperties": [],
							"typeProperties": {
								"variableName": "vr1",
								"value": 10
							}
						},
						{
							"name": "Wait2",
							"type": "Wait",
							"dependsOn": [
								{
									"activity": "Set variable1",
									"dependencyConditions": [
										"Succeeded"
									]
								}
							],
							"userProperties": [],
							"typeProperties": {
								"waitTimeInSeconds": {
									"value": "@variables('vr1')",
									"type": "Expression"
								}
							}
						}
					]
				}
			}
		],
		"variables": {
			"vr1": {
				"type": "Integer",
				"defaultValue": 3
			}
		},
		"annotations": [],
		"lastPublishTime": "2026-04-08T07:20:04Z"
	},
	"type": "Microsoft.DataFactory/factories/pipelines"
}